evo/__init__.py
evo/generation.py
evo/models.py
evo/scoring.py
evo/utils.py
evo/version.py
evo/configs/evo-1-131k-base_inference.yml
evo/configs/evo-1-8k-base_inference.yml
evo/scripts/example_inference.py
evo/scripts/generate.py
evo/scripts/generation_to_folding.py
evo/scripts/score.py
evo_model-0.4.dist-info/LICENSE
evo_model-0.4.dist-info/METADATA
evo_model-0.4.dist-info/WHEEL
evo_model-0.4.dist-info/top_level.txt
evo_model-0.4.dist-info/RECORD
