Metadata-Version: 2.1
Name: evo-model
Version: 0.4
Summary: DNA foundation modeling from molecular to genome scale.
Home-page: https://github.com/evo-design/evo
Author: Team Evo
License: Apache-2.0
Requires-Python: >=3.6
License-File: LICENSE
Requires-Dist: stripedhyena==0.2.2
Requires-Dist: biopython
Requires-Dist: pandas
Requires-Dist: triton
